book/_bookdown.yml
book/build_book.yml
book/colocalization.Rmd
book/compile.R
book/compile2.R
book/concat.Rmd
book/count_overlaps.Rmd
book/coverage.Rmd
book/creating.Rmd
book/custom_methods.Rmd
book/databases.Rmd
book/exons.py
book/fisher_exact.Rmd
book/genomicfeatures.Rmd
book/index.Rmd
book/insert.Rmd
book/intersection.Rmd
book/iterate.Rmd
book/join.Rmd
book/knearest.Rmd
book/make_book.py
book/manipulation.Rmd
book/mcc.Rmd
book/multithreading.Rmd
book/nearest.Rmd
book/piping.Rmd
book/printing.Rmd
book/pyranges.css
book/reldist.Rmd
book/rowbased_statistics.Rmd
book/runlength_dict.Rmd
book/runlengths.Rmd
book/simes.Rmd
book/single_range_methods.Rmd
book/sort.Rmd
book/subset.Rmd
book/subsetting_pyrles.Rmd
book/subsetting_rles.Rmd
book/subtract.Rmd
book/summary.Rmd
book/tutorial.Rmd
book/writing.Rmd
docs/Makefile
docs/_iframe.html
docs/_index.rst.html
docs/conf.py
docs/developer_guide.rst
docs/how_to_book_old_version.rst
docs/how_to_pages.rst
docs/index.rst
docs/installation.rst
docs/make.bat
docs/requirements.txt
docs/tutorial.rst
graphs/hypothesis-tested-brightgreen.svg
graphs/main_paper_annotation_binary.png
graphs/memory.png
graphs/time.png
pyranges/__init__.py
pyranges/data.py
pyranges/docs
pyranges/genomicfeatures.py
pyranges/get_fasta.py
pyranges/helpers.py
pyranges/multioverlap.py
pyranges/multithreaded.py
pyranges/out.py
pyranges/pyranges_main.py
pyranges/readers.py
pyranges/statistics.py
pyranges/stats.py
pyranges/subset.py
pyranges/tostring2.py
pyranges/example_data/aorta.bed
pyranges/example_data/aorta2.bed
pyranges/example_data/bw.bw
pyranges/example_data/chipseq.bed
pyranges/example_data/chipseq_background.bed
pyranges/example_data/chromsizes.bed
pyranges/example_data/control.bam
pyranges/example_data/control.bam.bai
pyranges/example_data/cpg.bed
pyranges/example_data/ensembl.gtf
pyranges/example_data/ensembl_human.gtf.gz
pyranges/example_data/exons.bed
pyranges/example_data/f1.bed
pyranges/example_data/f2.bed
pyranges/example_data/gencode_human.gtf.gz
pyranges-0.1.4.dist-info/LICENSE
pyranges-0.1.4.dist-info/METADATA
pyranges-0.1.4.dist-info/WHEEL
pyranges-0.1.4.dist-info/top_level.txt
pyranges-0.1.4.dist-info/RECORD
