Metadata-Version: 2.2
Name: pyranges
Version: 0.1.4
Summary: GenomicRanges for Python.
Author-email: Endre Bakken Stovner <endbak@pm.me>, Marco Mariotti <marco.mariotti@ub.edu>
License: MIT
Project-URL: Homepage, http://github.com/pyranges/pyranges
Keywords: bioinformatics,genomicranges,genomics
Classifier: Programming Language :: Python :: 3
Classifier: Development Status :: 4 - Beta
Classifier: Environment :: Other Environment
Classifier: Intended Audience :: Developers
Classifier: Intended Audience :: Science/Research
Classifier: License :: OSI Approved :: MIT License
Classifier: Operating System :: POSIX :: Linux
Classifier: Operating System :: MacOS :: MacOS X
Classifier: Topic :: Scientific/Engineering
License-File: LICENSE
Requires-Dist: pandas
Requires-Dist: ncls>=0.0.63
Requires-Dist: tabulate
Requires-Dist: sorted_nearest>=0.0.33
Requires-Dist: natsort
Provides-Extra: dev
Requires-Dist: black==24.4.2; extra == "dev"
Requires-Dist: bumpver; extra == "dev"
Requires-Dist: isort==5.13.2; extra == "dev"
Requires-Dist: pip-tools; extra == "dev"
Requires-Dist: pytest==7.4.3; extra == "dev"
Requires-Dist: mypy==1.8.0; extra == "dev"
